{
  "doc_id": "79257",
  "url": "https://www.legis.la.gov/legis/Law.aspx?d=79257",
  "citation": "RS 15:581",
  "title": "Authorized audits and investigations",
  "downloaded_at_epoch": 1771536862,
  "doc_html": "<p align=\"justify\" class=\"A0001\">§581.  Authorized audits and investigations</p>\n<p align=\"justify\" class=\"A0002\">With the written authorization of the deputy secretary, any employee or agent of the bureau, for purpose of audit or investigation of violations of any provisions herein, or any official rule or regulation of the bureau, shall be granted access by any public or private criminal justice agency collecting, processing, storing, or maintaining any documents, or automated, microfilmed, or manual records containing, or which may reasonably be expected to be used to substantiate and verify, any information or statistics the bureau is empowered to require from such public or private criminal justice agency.  Upon written authorization of the deputy secretary, any employee or agent of the bureau may enter any institution to which persons have been committed, who have been convicted of crime, or declared to be criminally insane or to be delinquents with intellectual disabilities, to take or cause to be taken fingerprints or photographs or to make investigations relative to any person confined therein, for the purpose of obtaining information which will lead to the identification of criminals.</p>\n<p align=\"justify\" class=\"A0002\">Acts 1981, No. 449, §1, eff. July 1, 1981; Acts 2014, No. 811, §7, eff. June 23, 2014.</p>",
  "doc_text": "§581.  Authorized audits and investigations\nWith the written authorization of the deputy secretary, any employee or agent of the bureau, for purpose of audit or investigation of violations of any provisions herein, or any official rule or regulation of the bureau, shall be granted access by any public or private criminal justice agency collecting, processing, storing, or maintaining any documents, or automated, microfilmed, or manual records containing, or which may reasonably be expected to be used to substantiate and verify, any information or statistics the bureau is empowered to require from such public or private criminal justice agency.  Upon written authorization of the deputy secretary, any employee or agent of the bureau may enter any institution to which persons have been committed, who have been convicted of crime, or declared to be criminally insane or to be delinquents with intellectual disabilities, to take or cause to be taken fingerprints or photographs or to make investigations relative to any person confined therein, for the purpose of obtaining information which will lead to the identification of criminals.\nActs 1981, No. 449, §1, eff. July 1, 1981; Acts 2014, No. 811, §7, eff. June 23, 2014."
}
