{
  "doc_id": "79262",
  "url": "https://www.legis.la.gov/legis/Law.aspx?d=79262",
  "citation": "RS 15:586",
  "title": "Authority to purge records of the central repository",
  "downloaded_at_epoch": 1771536862,
  "doc_html": "<p align=\"justify\" class=\"A0001\">§586.  Authority to purge records of the central repository </p>\n<p align=\"justify\" class=\"A0002\">Except for the provisions of R.S. 44:9, no records of the bureau may be permanently destroyed until five years after the person identified is known or reasonably believed to be dead.  Upon the official issuance of appropriate rules and regulations, the bureau may retire or remove from active dissemination to eligible agencies records of any individual beyond the age of sixty, who has had no reported criminal arrest for a period of fifteen years from the last reported official release from the criminal justice system.  </p>\n<p align=\"justify\" class=\"A0002\">Acts 1981, No. 449, §1, eff. July 1, 1981.  </p>",
  "doc_text": "§586.  Authority to purge records of the central repository\nExcept for the provisions of R.S. 44:9, no records of the bureau may be permanently destroyed until five years after the person identified is known or reasonably believed to be dead.  Upon the official issuance of appropriate rules and regulations, the bureau may retire or remove from active dissemination to eligible agencies records of any individual beyond the age of sixty, who has had no reported criminal arrest for a period of fifteen years from the last reported official release from the criminal justice system.\nActs 1981, No. 449, §1, eff. July 1, 1981."
}
