{
  "doc_id": "669805",
  "url": "https://www.legis.la.gov/legis/Law.aspx?d=669805",
  "citation": "CC 178",
  "title": "Definition",
  "downloaded_at_epoch": 1771968445,
  "doc_html": "<p align=\"center\" class=\"A0001\">TITLE VII.  PARENT AND CHILD</p>\n<p align=\"center\" class=\"A0001\">CHAPTER 1.  FILIATION</p>\n<p align=\"justify\" class=\"A0002\">Art. 178.  Definition</p>\n<p align=\"justify\" class=\"A0003\">Filiation is the legal relationship between a child and his parent.</p>\n<p align=\"justify\" class=\"A0003\">Acts 2009, No. 3, §1, eff. June 9, 2009.</p>\n<p align=\"justify\" class=\"A0004\"><br/></p>",
  "doc_text": "TITLE VII.  PARENT AND CHILD\nCHAPTER 1.  FILIATION\nArt. 178.  Definition\nFiliation is the legal relationship between a child and his parent.\nActs 2009, No. 3, §1, eff. June 9, 2009."
}
