{
  "doc_id": "112228",
  "url": "https://www.legis.la.gov/legis/Law.aspx?d=112228",
  "citation": "CCP 71",
  "title": "Action against individual who has changed domicile",
  "downloaded_at_epoch": 1771968618,
  "doc_html": "<p align=\"center\" class=\"A0001\">SECTION 2.  EXCEPTIONS TO GENERAL RULES</p>\n<p align=\"justify\" class=\"A0002\">Art. 71.  Action against individual who has changed domicile </p>\n<p align=\"justify\" class=\"A0003\">An action against an individual who has changed his domicile from one parish to another may be brought in either parish for a period of one year from the date of the change, unless he has filed a declaration of intention to change his domicile, in the manner provided by law.</p>",
  "doc_text": "SECTION 2.  EXCEPTIONS TO GENERAL RULES\nArt. 71.  Action against individual who has changed domicile\nAn action against an individual who has changed his domicile from one parish to another may be brought in either parish for a period of one year from the date of the change, unless he has filed a declaration of intention to change his domicile, in the manner provided by law."
}
