{
  "doc_id": "99806",
  "url": "https://www.legis.la.gov/legis/Law.aspx?d=99806",
  "citation": "RS 45:1161.3",
  "title": "District staffing",
  "downloaded_at_epoch": 1771966820,
  "doc_html": "<p align=\"justify\" class=\"A0001\">§1161.3.  District staffing</p>\n<p align=\"justify\" class=\"A0002\">There shall be thirty-seven full-time employee positions available for district staffing, the allocation of which per district shall be as determined by the commission. </p>\n<p align=\"justify\" class=\"A0002\">Added by Acts 1975, No. 4, §1, eff. June 13, 1975.  Amended by Acts 1981, Ex.Sess., No. 19, §1, eff. July 1, 1982; Acts 1992, No. 23, §1, eff. May 22, 1992; Acts 1992, No. 871, §1, eff. July 1, 1993; Acts 2001, 2nd Ex. Sess., No. 2, §§5, 6, eff. Jan. 1, 2003. </p>\n<p align=\"justify\" class=\"A0003\">NOTE:  See Acts 2001, 2nd Ex. Sess., No. 2, §§2-4 and 7, relative to effectiveness of this provisions.</p>",
  "doc_text": "§1161.3.  District staffing\nThere shall be thirty-seven full-time employee positions available for district staffing, the allocation of which per district shall be as determined by the commission.\nAdded by Acts 1975, No. 4, §1, eff. June 13, 1975.  Amended by Acts 1981, Ex.Sess., No. 19, §1, eff. July 1, 1982; Acts 1992, No. 23, §1, eff. May 22, 1992; Acts 1992, No. 871, §1, eff. July 1, 1993; Acts 2001, 2nd Ex. Sess., No. 2, §§5, 6, eff. Jan. 1, 2003.\nNOTE:  See Acts 2001, 2nd Ex. Sess., No. 2, §§2-4 and 7, relative to effectiveness of this provisions."
}
