{
  "doc_id": "80084",
  "url": "https://www.legis.la.gov/legis/Law.aspx?d=80084",
  "citation": "RS 17:1970.23",
  "title": "New Orleans Center for Creative Arts; creation; purpose; governance",
  "downloaded_at_epoch": 1771537249,
  "doc_html": "<div id=\"WPMainDoc\">\n<p style=\"text-indent: -0.5in; margin-left: 0.5in\">§1970.23.  New Orleans Center for Creative Arts; creation; purpose; governance</p>\n<p><span>           </span>A.  There is hereby created the New Orleans Center for the Creative Arts which\r\nshall be a state center primarily for the training of high school students operated in a\r\nfacility owned by the state which was designed and built to house a program of\r\nprofessional quality training, coaching, and performing for students who aspire to be\r\nartists, performers, and arts technicians.  The center shall provide for the enrollment of\r\nqualified students from the state of Louisiana.  The center shall begin operation as a state\r\ncenter as provided in this Part beginning July 1, 2000.  The center shall be an agency of\r\nstate government and shall be independent of the control of the state superintendent and\r\nof all local and state education boards, except the New Orleans Center for the Creative\r\nArts board of directors.</p>\n<p><span>           </span>B.  The center shall be governed and managed by a board of directors the\r\nmembership of which and the powers and duties of which shall be as provided in this\r\nPart.</p>\n<p><span>           </span>Acts 2000, 1st Ex. Sess., No. 60, §2, eff. July 1, 2000; Acts 2010, No. 525, §2, eff.\r\nJune 24, 2010.</p>\n</div>",
  "doc_text": "§1970.23.  New Orleans Center for Creative Arts; creation; purpose; governance\nA.  There is hereby created the New Orleans Center for the Creative Arts which\nshall be a state center primarily for the training of high school students operated in a\nfacility owned by the state which was designed and built to house a program of\nprofessional quality training, coaching, and performing for students who aspire to be\nartists, performers, and arts technicians.  The center shall provide for the enrollment of\nqualified students from the state of Louisiana.  The center shall begin operation as a state\ncenter as provided in this Part beginning July 1, 2000.  The center shall be an agency of\nstate government and shall be independent of the control of the state superintendent and\nof all local and state education boards, except the New Orleans Center for the Creative\nArts board of directors.\nB.  The center shall be governed and managed by a board of directors the\nmembership of which and the powers and duties of which shall be as provided in this\nPart.\nActs 2000, 1st Ex. Sess., No. 60, §2, eff. July 1, 2000; Acts 2010, No. 525, §2, eff.\nJune 24, 2010."
}
