{
  "doc_id": "95675",
  "url": "https://www.legis.la.gov/legis/Law.aspx?d=95675",
  "citation": "RS 39:1",
  "title": "TITLE 39.PUBLIC FINANCE",
  "downloaded_at_epoch": 1771966391,
  "doc_html": "<p align=\"center\" class=\"A0001\">TITLE 39.  PUBLIC FINANCE</p>\n<p align=\"center\" class=\"A0001\">SUBTITLE I.  STATE FINANCE</p>\n<p align=\"center\" class=\"A0001\">CHAPTER 1.  DIVISION OF ADMINISTRATION</p>\n<p align=\"center\" class=\"A0001\">PART I.  DIVISION OF ADMINISTRATION</p>\n<p align=\"center\" class=\"A0001\">SUBPART A.  ORGANIZATION</p>\n<p align=\"justify\" class=\"A0002\">§1.  Division of administration</p>\n<p align=\"justify\" class=\"A0003\">A division of administration is hereby created as a division of the office of the governor and shall exercise those powers and functions as hereinafter set forth and as may be further provided by law.</p>\n<p align=\"justify\" class=\"A0003\">Amended by Acts 1952, No. 58, §1; Acts 1956, No. 42, §1; Acts 1989, No. 836, §1, eff.  July 1, 1989.</p>",
  "doc_text": "TITLE 39.  PUBLIC FINANCE\nSUBTITLE I.  STATE FINANCE\nCHAPTER 1.  DIVISION OF ADMINISTRATION\nPART I.  DIVISION OF ADMINISTRATION\nSUBPART A.  ORGANIZATION\n§1.  Division of administration\nA division of administration is hereby created as a division of the office of the governor and shall exercise those powers and functions as hereinafter set forth and as may be further provided by law.\nAmended by Acts 1952, No. 58, §1; Acts 1956, No. 42, §1; Acts 1989, No. 836, §1, eff.  July 1, 1989."
}
