{
  "doc_id": "87794",
  "url": "https://www.legis.la.gov/legis/Law.aspx?d=87794",
  "citation": "RS 31:105",
  "title": "EXECUTIVE RIGHTS",
  "downloaded_at_epoch": 1771965653,
  "doc_html": "<p align=\"center\" class=\"A0001\">CHAPTER 6.  EXECUTIVE RIGHTS</p>\n<p align=\"justify\" class=\"A0002\">§105.  Nature of executive right </p>\n<p align=\"justify\" class=\"A0003\">The executive right is the exclusive right to grant mineral leases of specified land or mineral rights.  Unless restricted by contract it includes the right to retain bonuses and rentals.  The owner of the executive right may lease the land or mineral rights over which he has power to the same extent and on such terms and conditions as if he were the owner of a mineral servitude.  </p>\n<p align=\"justify\" class=\"A0003\">Acts 1974, No. 50, §105, eff. Jan. 1, 1975.  </p>",
  "doc_text": "CHAPTER 6.  EXECUTIVE RIGHTS\n§105.  Nature of executive right\nThe executive right is the exclusive right to grant mineral leases of specified land or mineral rights.  Unless restricted by contract it includes the right to retain bonuses and rentals.  The owner of the executive right may lease the land or mineral rights over which he has power to the same extent and on such terms and conditions as if he were the owner of a mineral servitude.\nActs 1974, No. 50, §105, eff. Jan. 1, 1975."
}
