{
  "doc_id": "112715",
  "url": "https://www.legis.la.gov/legis/Law.aspx?d=112715",
  "citation": "CCRP 708",
  "title": "Continuance and recess; definitions",
  "downloaded_at_epoch": 1771968705,
  "doc_html": "<p align=\"justify\" class=\"A0001\">Art. 708.  Continuance and recess; definitions </p>\n<p align=\"justify\" class=\"A0002\">A continuance is the postponement of a scheduled trial or hearing, and shall not be granted after the trial or hearing has commenced.  A recess is a temporary adjournment of a trial or hearing that occurs after a trial or hearing has commenced.</p>",
  "doc_text": "Art. 708.  Continuance and recess; definitions\nA continuance is the postponement of a scheduled trial or hearing, and shall not be granted after the trial or hearing has commenced.  A recess is a temporary adjournment of a trial or hearing that occurs after a trial or hearing has commenced."
}
