{
  "doc_id": "180525",
  "url": "https://www.legis.la.gov/legis/Law.aspx?d=180525",
  "citation": "SRULE 6.2",
  "title": "Decorous language",
  "downloaded_at_epoch": 1771968784,
  "doc_html": "<p class=\"A0001\">Rule 6.2.  Decorous language </p>\n<p class=\"A0002\">Every member shall confine himself to decorous language in addressing the Senate and shall make no personal or derogatory remark to or about any member. </p>",
  "doc_text": "Rule 6.2.  Decorous language\nEvery member shall confine himself to decorous language in addressing the Senate and shall make no personal or derogatory remark to or about any member."
}
