{
  "doc_id": "1108922",
  "url": "https://www.legis.la.gov/legis/Law.aspx?d=1108922",
  "citation": "RS 37:1208.1",
  "title": "Waiver of license or certificate renewal fee for military spouse",
  "downloaded_at_epoch": 1771966205,
  "doc_html": "<div id=\"WPMainDoc\">\n<p style=\"text-align:left; text-indent: -0.5in; margin-left: 0.5in\"><span style=\"font-family: 'Times New Roman', serif\"><span style=\"font-size: 12pt\">§1208.1.  Waiver of license or certificate renewal fee for military spouse</span></span></p>\n<p style=\"text-align:left\"><span style=\"font-family: 'Times New Roman', serif\"><span style=\"font-size: 12pt\"><span>            </span>Upon written request of any licensed pharmacist or certified technician who is the\r\nspouse of an active-duty member of the armed forces of the United States, the board may\r\nwaive the requirement of the fee for the renewal of a pharmacist license or technician\r\ncertificate in accordance with the rules promulgated by the board.</span></span></p>\n<p style=\"text-align:left\"><span style=\"font-family: 'Times New Roman', serif\"><span style=\"font-size: 12pt\"><span>            </span>Acts 2018, No. 63, §1.</span></span></p>\n</div>",
  "doc_text": "§1208.1.  Waiver of license or certificate renewal fee for military spouse\nUpon written request of any licensed pharmacist or certified technician who is the\nspouse of an active-duty member of the armed forces of the United States, the board may\nwaive the requirement of the fee for the renewal of a pharmacist license or technician\ncertificate in accordance with the rules promulgated by the board.\nActs 2018, No. 63, §1."
}
