{
  "doc_id": "93989",
  "url": "https://www.legis.la.gov/legis/Law.aspx?d=93989",
  "citation": "RS 37:3202",
  "title": "Terms of members; vacancies",
  "downloaded_at_epoch": 1771966215,
  "doc_html": "<p align=\"justify\" class=\"A0001\">§3202.  Terms of members; vacancies </p>\n<p align=\"justify\" class=\"A0002\">A.  The members of the board shall serve at the pleasure of the appointing governor.  </p>\n<p align=\"justify\" class=\"A0002\">B.  Vacancies shall be filled for an unexpired term in the manner of original appointment.  </p>\n<p align=\"justify\" class=\"A0002\">Acts 1984, No. 485, §1.  </p>",
  "doc_text": "§3202.  Terms of members; vacancies\nA.  The members of the board shall serve at the pleasure of the appointing governor.\nB.  Vacancies shall be filled for an unexpired term in the manner of original appointment.\nActs 1984, No. 485, §1."
}
