{
  "doc_id": "94237",
  "url": "https://www.legis.la.gov/legis/Law.aspx?d=94237",
  "citation": "RS 37:368",
  "title": "Permits for barbers pending examination",
  "downloaded_at_epoch": 1771966200,
  "doc_html": "<p align=\"justify\" class=\"A0001\">§368.  Permits for barbers pending examination </p>\n<p align=\"justify\" class=\"A0002\">Any person who holds a valid current license to engage in the practice of barbering issued by any state of the United States or any foreign country may be issued a temporary permit to engage in the practice of barbering in this state pending examination by the board upon payment of the permit fee set by the board.  </p>\n<p align=\"justify\" class=\"A0002\">Acts 1964, No. 309, §1.  Amended by Acts 1976, No. 424, §6; Acts 1984, No. 238, §1.  </p>",
  "doc_text": "§368.  Permits for barbers pending examination\nAny person who holds a valid current license to engage in the practice of barbering issued by any state of the United States or any foreign country may be issued a temporary permit to engage in the practice of barbering in this state pending examination by the board upon payment of the permit fee set by the board.\nActs 1964, No. 309, §1.  Amended by Acts 1976, No. 424, §6; Acts 1984, No. 238, §1."
}
